easyAI/Player.py
easyAI/TwoPlayerGame.py
easyAI/__init__.py
easyAI/version.py
easyAI/AI/DUAL.py
easyAI/AI/DictTranspositionTable.py
easyAI/AI/HashTranspositionTable.py
easyAI/AI/Hashes.py
easyAI/AI/MTdriver.py
easyAI/AI/Negamax.py
easyAI/AI/NonRecursiveNegamax.py
easyAI/AI/SSS.py
easyAI/AI/TranspositionTable.py
easyAI/AI/__init__.py
easyAI/AI/solving.py
easyAI/games/Awele.py
easyAI/games/AweleTactical.py
easyAI/games/Chopsticks.py
easyAI/games/ConnectFour.py
easyAI/games/Cram.py
easyAI/games/GameOfBones.py
easyAI/games/Hexapawn.py
easyAI/games/Knights-Kivy.py
easyAI/games/Knights.py
easyAI/games/Nim.py
easyAI/games/Reversi.py
easyAI/games/ThreeMusketeers.py
easyAI/games/TicTacToe-Flask.py
easyAI/games/TicTacToe.py
easyAI/games/__init__.py
easyAI-2.0.12.dist-info/LICENCE.txt
easyAI-2.0.12.dist-info/METADATA
easyAI-2.0.12.dist-info/WHEEL
easyAI-2.0.12.dist-info/top_level.txt
easyAI-2.0.12.dist-info/RECORD
