Metadata-Version: 1.0
Name: easyAI
Version: 2.0.12
Summary: Easy-to-use game AI algorithms (Negamax etc. )
Home-page: UNKNOWN
Author: UNKNOWN
Author-email: UNKNOWN
License: LICENSE.txt
Keywords: board games AI artificial intelligence negamax
Platform: UNKNOWN
